odoo/addons/fieldservice_stock/README.rst
odoo/addons/fieldservice_stock/__init__.py
odoo/addons/fieldservice_stock/__manifest__.py
odoo/addons/fieldservice_stock/data/fsm_stock_data.xml
odoo/addons/fieldservice_stock/i18n/de.po
odoo/addons/fieldservice_stock/i18n/es.po
odoo/addons/fieldservice_stock/i18n/es_CL.po
odoo/addons/fieldservice_stock/i18n/fieldservice_stock.pot
odoo/addons/fieldservice_stock/i18n/pt_BR.po
odoo/addons/fieldservice_stock/models/__init__.py
odoo/addons/fieldservice_stock/models/fsm_location.py
odoo/addons/fieldservice_stock/models/fsm_order.py
odoo/addons/fieldservice_stock/models/fsm_territory.py
odoo/addons/fieldservice_stock/models/fsm_wizard.py
odoo/addons/fieldservice_stock/models/procurement_group.py
odoo/addons/fieldservice_stock/models/stock_move.py
odoo/addons/fieldservice_stock/models/stock_picking.py
odoo/addons/fieldservice_stock/models/stock_rule.py
odoo/addons/fieldservice_stock/readme/CONFIGURE.rst
odoo/addons/fieldservice_stock/readme/CONTRIBUTORS.rst
odoo/addons/fieldservice_stock/readme/CREDITS.rst
odoo/addons/fieldservice_stock/readme/DESCRIPTION.rst
odoo/addons/fieldservice_stock/readme/INSTALL.rst
odoo/addons/fieldservice_stock/readme/ROADMAP.rst
odoo/addons/fieldservice_stock/readme/USAGE.rst
odoo/addons/fieldservice_stock/security/ir.model.access.csv
odoo/addons/fieldservice_stock/static/description/icon.png
odoo/addons/fieldservice_stock/static/description/index.html
odoo/addons/fieldservice_stock/tests/__init__.py
odoo/addons/fieldservice_stock/tests/common.py
odoo/addons/fieldservice_stock/views/fsm_location.xml
odoo/addons/fieldservice_stock/views/fsm_order.xml
odoo/addons/fieldservice_stock/views/fsm_territory.xml
odoo/addons/fieldservice_stock/views/stock.xml
odoo12_addon_fieldservice_stock-12.0.3.0.1.dist-info/METADATA
odoo12_addon_fieldservice_stock-12.0.3.0.1.dist-info/WHEEL
odoo12_addon_fieldservice_stock-12.0.3.0.1.dist-info/top_level.txt
odoo12_addon_fieldservice_stock-12.0.3.0.1.dist-info/RECORD
